avalon_consumer.v
// =============================================================================
// avalon_consumer.v
//
// Avalon-ST SINK. This module was referenced by the original avalon_test.v
// top level but never actually existed in the project - the design could not
// elaborate without it. It is added here to complete the architecture.
//
// Behaviour: accepts one byte per valid/ready handshake and latches it into
// an output register (e.g. LEDs). An optional stall generator can be enabled
// (STALL_PERIOD != 0) to model a sink that occasionally can't accept data,
// which exercises the upstream source's valid/ready backpressure handling in
// simulation.
// =============================================================================

module avalon_consumer #(
    parameter STALL_PERIOD = 0   // assert !ready for 1 cycle every N accepted
                                  // transfers (0 = always ready, no backpressure)
)(
    input  wire       clk,
    input  wire       reset_n,

    // Avalon-ST Sink Interface (asi)
    input  wire [7:0] asi_data,
    input  wire       asi_valid,
    output reg        asi_ready,

    output reg  [7:0] led_output,     // last accepted byte, mirrored on LEDs
    output reg [15:0] xfer_count      // debug: total accepted transfers
);

    reg [15:0] stall_ctr;

    always @(posedge clk or negedge reset_n) begin
        if (!reset_n) begin
            asi_ready  <= 1'b1;
            led_output <= 8'd0;
            xfer_count <= 16'd0;
            stall_ctr  <= 16'd0;
        end else begin

            // Default: ready, unless the stall generator says otherwise
            asi_ready <= 1'b1;

            if (asi_valid && asi_ready) begin
                led_output <= asi_data;
                xfer_count <= xfer_count + 16'd1;

                if (STALL_PERIOD != 0) begin
                    if (stall_ctr == STALL_PERIOD - 1) begin
                        asi_ready <= 1'b0;   // insert one cycle of backpressure
                        stall_ctr <= 16'd0;
                    end else begin
                        stall_ctr <= stall_ctr + 16'd1;
                    end
                end
            end
        end
    end

endmodule

avalon_producer.v
// =============================================================================
// avalon_producer.v
//
// Simple free-running Avalon-ST SOURCE that just counts up (0,1,2,...,255,0,...)
// and offers a new byte every cycle the sink is ready for. Kept from the
// original project as a lightweight, standalone alternative source IP for
// simple bring-up/test scenarios where a full DMA engine isn't needed -
// logic is unchanged from the original, only comments clarify the protocol.
// =============================================================================

module avalon_producer (
    input  wire       clk,
    input  wire       reset_n,

    // Avalon-ST Source Interface (aso)
    output reg [7:0]  aso_data,   // 8-bit data
    output reg        aso_valid,  // "Here is data"
    input  wire       aso_ready   // "Can you take it?"
);

    always @(posedge clk or negedge reset_n) begin
        if (!reset_n) begin
            aso_data  <= 8'd0;
            aso_valid <= 1'b0;
        end else begin
            // We always have data to give
            aso_valid <= 1'b1;

            // THE AVALON HANDSHAKE (latency 0):
            // Advance the counter only once the sink actually accepts data
            if (aso_valid && aso_ready) begin
                aso_data <= aso_data + 1'b1;
            end
        end
    end
endmodule

tb_producer_consumer.v
// =============================================================================
// tb_producer_consumer.v
//
// Secondary testbench: exercises the simple standalone path
// avalon_producer -> avalon_consumer (no DMA / no memory), to demonstrate
// that avalon_producer.v is independently reusable as its own small IP
// block and that the basic Avalon-ST valid/ready handshake is correct.
//
// Self-checks that the byte stream landing on led_output is the free-running
// counter sequence 0,1,2,...,255,0,... with no skips or repeats, even with
// sink backpressure enabled.
// =============================================================================

`timescale 1ns/1ps

module tb_producer_consumer;

    localparam CLK_PERIOD = 20;

    reg clk;
    reg reset_n;

    wire [7:0] stream_data;
    wire       stream_valid;
    wire       stream_ready;
    wire [7:0] led_output;
    wire [15:0] xfer_count;

    avalon_producer u_producer (
        .clk       (clk),
        .reset_n   (reset_n),
        .aso_data  (stream_data),
        .aso_valid (stream_valid),
        .aso_ready (stream_ready)
    );

    avalon_consumer #(
        .STALL_PERIOD (5)   // exercise sink backpressure
    ) u_consumer (
        .clk        (clk),
        .reset_n    (reset_n),
        .asi_data   (stream_data),
        .asi_valid  (stream_valid),
        .asi_ready  (stream_ready),
        .led_output (led_output),
        .xfer_count (xfer_count)
    );

    always #(CLK_PERIOD/2) clk = ~clk;

    initial begin
        clk     = 1'b0;
        reset_n = 1'b0;
        repeat (5) @(posedge clk);
        reset_n = 1'b1;
    end

    initial begin
        $dumpfile("producer_consumer.vcd");
        $dumpvars(0, tb_producer_consumer);
    end

    // Expected value = previous accepted value + 1 (starts at 0)
    reg [7:0] expected;
    integer   checked;
    integer   errors;

    initial begin
        expected = 8'd0;
        checked  = 0;
        errors   = 0;
    end

    always @(posedge clk) begin
        if (reset_n && stream_valid && stream_ready) begin
            checked <= checked + 1;
            if (stream_data !== expected) begin
                $display("[%0t] MISMATCH #%0d: got 0x%02h expected 0x%02h",
                          $time, checked, stream_data, expected);
                errors <= errors + 1;
            end
            expected <= expected + 8'd1;
        end
    end

    initial begin
        wait (reset_n === 1'b1);
        repeat (600) @(posedge clk);

        $display("--------------------------------------------------");
        $display(" PRODUCER/CONSUMER TEST SUMMARY");
        $display("   transfers checked : %0d", checked);
        $display("   mismatches        : %0d", errors);
        $display("   RESULT            : %s", (checked > 0 && errors == 0) ? "PASS" : "FAIL");
        $display("--------------------------------------------------");

        $finish;
    end

endmodule

producer_consumer.vcd
$date
	Tue Jul  7 07:08:46 2026
$end
$version
	Icarus Verilog
$end
$timescale
	1ps
$end
$scope module tb_producer_consumer $end
$var wire 16 ! xfer_count [15:0] $end
$var wire 1 " stream_valid $end
$var wire 1 # stream_ready $end
$var wire 8 $ stream_data [7:0] $end
$var wire 8 % led_output [7:0] $end
$var parameter 32 & CLK_PERIOD $end
$var reg 1 ' clk $end
$var reg 8 ( expected [7:0] $end
$var reg 1 ) reset_n $end
$var integer 32 * checked [31:0] $end
$var integer 32 + errors [31:0] $end
$scope module u_consumer $end
$var wire 1 ' clk $end
$var wire 1 ) reset_n $end
$var wire 1 " asi_valid $end
$var wire 8 , asi_data [7:0] $end
$var parameter 32 - STALL_PERIOD $end
$var reg 1 # asi_ready $end
$var reg 8 . led_output [7:0] $end
$var reg 16 / stall_ctr [15:0] $end
$var reg 16 0 xfer_count [15:0] $end
$upscope $end
$scope module u_producer $end
$var wire 1 # aso_ready $end
$var wire 1 ' clk $end
$var wire 1 ) reset_n $end
$var reg 8 1 aso_data [7:0] $end
$var reg 1 " aso_valid $end
$upscope $end
$upscope $end
$enddefinitions $end
$comment Show the parameter values. $end
$dumpall
b101 -
b10100 &
$end
#0
$dumpvars
b0 1
b0 0
b0 /
b0 .
b0 ,
b0 +
b0 *
0)
b0 (
0'
b0 %
b0 $
1#
0"
b0 !
$end
#10000
1'
#20000
0'
#30000
1'
#40000
0'
#50000
1'
#60000
0'
#70000
1'
#80000
0'
#90000
1"
1)
1'
#100000
0'
#110000
b1 $
b1 ,
b1 1
b1 /
b1 !
b1 0
b1 (
b1 *
1'
#120000
0'
#130000
b10 /
b10 !
b10 0
b1 %
b1 .
b10 $
b10 ,
b10 1
b10 (
b10 *
1'
#140000
0'
#150000
b11 $
b11 ,
b11 1
b11 /
b11 !
b11 0
b10 %
b10 .
b11 (
b11 *
1'
#160000
0'
#170000
b100 /
b100 !
b100 0
b11 %
b11 .
b100 $
b100 ,
b100 1
b100 (
b100 *
1'
#180000
0'
#190000
b101 $
b101 ,
b101 1
b0 /
0#
b101 !
b101 0
b100 %
b100 .
b101 (
b101 *
1'
#200000
0'
#210000
1#
1'
#220000
0'
#230000
b110 $
b110 ,
b110 1
b1 /
b110 !
b110 0
b101 %
b101 .
b110 (
b110 *
1'
#240000
0'
#250000
b10 /
b111 !
b111 0
b110 %
b110 .
b111 $
b111 ,
b111 1
b111 (
b111 *
1'
#260000
0'
#270000
b1000 $
b1000 ,
b1000 1
b11 /
b1000 !
b1000 0
b111 %
b111 .
b1000 (
b1000 *
1'
#280000
0'
#290000
b100 /
b1001 !
b1001 0
b1000 %
b1000 .
b1001 $
b1001 ,
b1001 1
b1001 (
b1001 *
1'
#300000
0'
#310000
b1010 $
b1010 ,
b1010 1
b0 /
0#
b1010 !
b1010 0
b1001 %
b1001 .
b1010 (
b1010 *
1'
#320000
0'
#330000
1#
1'
#340000
0'
#350000
b1011 $
b1011 ,
b1011 1
b1 /
b1011 !
b1011 0
b1010 %
b1010 .
b1011 (
b1011 *
1'
#360000
0'
#370000
b10 /
b1100 !
b1100 0
b1011 %
b1011 .
b1100 $
b1100 ,
b1100 1
b1100 (
b1100 *
1'
#380000
0'
#390000
b1101 $
b1101 ,
b1101 1
b11 /
b1101 !
b1101 0
b1100 %
b1100 .
b1101 (
b1101 *
1'
#400000
0'
#410000
b100 /
b1110 !
b1110 0
b1101 %
b1101 .
b1110 $
b1110 ,
b1110 1
b1110 (
b1110 *
1'
#420000
0'
#430000
b1111 $
b1111 ,
b1111 1
b0 /
0#
b1111 !
b1111 0
b1110 %
b1110 .
b1111 (
b1111 *
1'
#440000
0'
#450000
1#
1'
#460000
0'
#470000
b10000 $
b10000 ,
b10000 1
b1 /
b10000 !
b10000 0
b1111 %
b1111 .
b10000 (
b10000 *
1'
#480000
0'
#490000
b10 /
b10001 !
b10001 0
b10000 %
b10000 .
b10001 $
b10001 ,
b10001 1
b10001 (
b10001 *
1'
#500000
0'
#510000
b10010 $
b10010 ,
b10010 1
b11 /
b10010 !
b10010 0
b10001 %
b10001 .
b10010 (
b10010 *
1'
#520000
0'
#530000
b100 /
b10011 !
b10011 0
b10010 %
b10010 .
b10011 $
b10011 ,
b10011 1
b10011 (
b10011 *
1'
#540000
0'
#550000
b10100 $
b10100 ,
b10100 1
b0 /
0#
b10100 !
b10100 0
b10011 %
b10011 .
b10100 (
b10100 *
1'
#560000
0'
#570000
1#
1'
#580000
0'
#590000
b10101 $
b10101 ,
b10101 1
b1 /
b10101 !
b10101 0
b10100 %
b10100 .
b10101 (
b10101 *
1'
#600000
0'
#610000
b10 /
b10110 !
b10110 0
b10101 %
b10101 .
b10110 $
b10110 ,
b10110 1
b10110 (
b10110 *
1'
#620000
0'
#630000
b10111 $
b10111 ,
b10111 1
b11 /
b10111 !
b10111 0
b10110 %
b10110 .
b10111 (
b10111 *
1'
#640000
0'
#650000
b100 /
b11000 !
b11000 0
b10111 %
b10111 .
b11000 $
b11000 ,
b11000 1
b11000 (
b11000 *
1'
#660000
0'
#670000
b11001 $
b11001 ,
b11001 1
b0 /
0#
b11001 !
b11001 0
b11000 %
b11000 .
b11001 (
b11001 *
1'
#680000
0'
#690000
1#
1'
#700000
0'
#710000
b11010 $
b11010 ,
b11010 1
b1 /
b11010 !
b11010 0
b11001 %
b11001 .
b11010 (
b11010 *
1'
#720000
0'
#730000
b10 /
b11011 !
b11011 0
b11010 %
b11010 .
b11011 $
b11011 ,
b11011 1
b11011 (
b11011 *
1'
#740000
0'
#750000
b11100 $
b11100 ,
b11100 1
b11 /
b11100 !
b11100 0
b11011 %
b11011 .
b11100 (
b11100 *
1'
#760000
0'
#770000
b100 /
b11101 !
b11101 0
b11100 %
b11100 .
b11101 $
b11101 ,
b11101 1
b11101 (
b11101 *
1'
#780000
0'
#790000
b11110 $
b11110 ,
b11110 1
b0 /
0#
b11110 !
b11110 0
b11101 %
b11101 .
b11110 (
b11110 *
1'
#800000
0'
#810000
1#
1'
#820000
0'
#830000
b11111 $
b11111 ,
b11111 1
b1 /
b11111 !
b11111 0
b11110 %
b11110 .
b11111 (
b11111 *
1'
#840000
0'
#850000
b10 /
b100000 !
b100000 0
b11111 %
b11111 .
b100000 $
b100000 ,
b100000 1
b100000 (
b100000 *
1'
#860000
0'
#870000
b100001 $
b100001 ,
b100001 1
b11 /
b100001 !
b100001 0
b100000 %
b100000 .
b100001 (
b100001 *
1'
#880000
0'
#890000
b100 /
b100010 !
b100010 0
b100001 %
b100001 .
b100010 $
b100010 ,
b100010 1
b100010 (
b100010 *
1'
#900000
0'
#910000
b100011 $
b100011 ,
b100011 1
b0 /
0#
b100011 !
b100011 0
b100010 %
b100010 .
b100011 (
b100011 *
1'
#920000
0'
#930000
1#
1'
#940000
0'
#950000
b100100 $
b100100 ,
b100100 1
b1 /
b100100 !
b100100 0
b100011 %
b100011 .
b100100 (
b100100 *
1'
#960000
0'
#970000
b10 /
b100101 !
b100101 0
b100100 %
b100100 .
b100101 $
b100101 ,
b100101 1
b100101 (
b100101 *
1'
#980000
0'
#990000
b100110 $
b100110 ,
b100110 1
b11 /
b100110 !
b100110 0
b100101 %
b100101 .
b100110 (
b100110 *
1'
#1000000
0'
#1010000
b100 /
b100111 !
b100111 0
b100110 %
b100110 .
b100111 $
b100111 ,
b100111 1
b100111 (
b100111 *
1'
#1020000
0'
#1030000
b101000 $
b101000 ,
b101000 1
b0 /
0#
b101000 !
b101000 0
b100111 %
b100111 .
b101000 (
b101000 *
1'
#1040000
0'
#1050000
1#
1'
#1060000
0'
#1070000
b101001 $
b101001 ,
b101001 1
b1 /
b101001 !
b101001 0
b101000 %
b101000 .
b101001 (
b101001 *
1'
#1080000
0'
#1090000
b10 /
b101010 !
b101010 0
b101001 %
b101001 .
b101010 $
b101010 ,
b101010 1
b101010 (
b101010 *
1'
#1100000
0'
#1110000
b101011 $
b101011 ,
b101011 1
b11 /
b101011 !
b101011 0
b101010 %
b101010 .
b101011 (
b101011 *
1'
#1120000
0'
#1130000
b100 /
b101100 !
b101100 0
b101011 %
b101011 .
b101100 $
b101100 ,
b101100 1
b101100 (
b101100 *
1'
#1140000
0'
#1150000
b101101 $
b101101 ,
b101101 1
b0 /
0#
b101101 !
b101101 0
b101100 %
b101100 .
b101101 (
b101101 *
1'
#1160000
0'
#1170000
1#
1'
#1180000
0'
#1190000
b101110 $
b101110 ,
b101110 1
b1 /
b101110 !
b101110 0
b101101 %
b101101 .
b101110 (
b101110 *
1'
#1200000
0'
#1210000
b10 /
b101111 !
b101111 0
b101110 %
b101110 .
b101111 $
b101111 ,
b101111 1
b101111 (
b101111 *
1'
#1220000
0'
#1230000
b110000 $
b110000 ,
b110000 1
b11 /
b110000 !
b110000 0
b101111 %
b101111 .
b110000 (
b110000 *
1'
#1240000
0'
#1250000
b100 /
b110001 !
b110001 0
b110000 %
b110000 .
b110001 $
b110001 ,
b110001 1
b110001 (
b110001 *
1'
#1260000
0'
#1270000
b110010 $
b110010 ,
b110010 1
b0 /
0#
b110010 !
b110010 0
b110001 %
b110001 .
b110010 (
b110010 *
1'
#1280000
0'
#1290000
1#
1'
#1300000
0'
#1310000
b110011 $
b110011 ,
b110011 1
b1 /
b110011 !
b110011 0
b110010 %
b110010 .
b110011 (
b110011 *
1'
#1320000
0'
#1330000
b10 /
b110100 !
b110100 0
b110011 %
b110011 .
b110100 $
b110100 ,
b110100 1
b110100 (
b110100 *
1'
#1340000
0'
#1350000
b110101 $
b110101 ,
b110101 1
b11 /
b110101 !
b110101 0
b110100 %
b110100 .
b110101 (
b110101 *
1'
#1360000
0'
#1370000
b100 /
b110110 !
b110110 0
b110101 %
b110101 .
b110110 $
b110110 ,
b110110 1
b110110 (
b110110 *
1'
#1380000
0'
#1390000
b110111 $
b110111 ,
b110111 1
b0 /
0#
b110111 !
b110111 0
b110110 %
b110110 .
b110111 (
b110111 *
1'
#1400000
0'
#1410000
1#
1'
#1420000
0'
#1430000
b111000 $
b111000 ,
b111000 1
b1 /
b111000 !
b111000 0
b110111 %
b110111 .
b111000 (
b111000 *
1'
#1440000
0'
#1450000
b10 /
b111001 !
b111001 0
b111000 %
b111000 .
b111001 $
b111001 ,
b111001 1
b111001 (
b111001 *
1'
#1460000
0'
#1470000
b111010 $
b111010 ,
b111010 1
b11 /
b111010 !
b111010 0
b111001 %
b111001 .
b111010 (
b111010 *
1'
#1480000
0'
#1490000
b100 /
b111011 !
b111011 0
b111010 %
b111010 .
b111011 $
b111011 ,
b111011 1
b111011 (
b111011 *
1'
#1500000
0'
#1510000
b111100 $
b111100 ,
b111100 1
b0 /
0#
b111100 !
b111100 0
b111011 %
b111011 .
b111100 (
b111100 *
1'
#1520000
0'
#1530000
1#
1'
#1540000
0'
#1550000
b111101 $
b111101 ,
b111101 1
b1 /
b111101 !
b111101 0
b111100 %
b111100 .
b111101 (
b111101 *
1'
#1560000
0'
#1570000
b10 /
b111110 !
b111110 0
b111101 %
b111101 .
b111110 $
b111110 ,
b111110 1
b111110 (
b111110 *
1'
#1580000
0'
#1590000
b111111 $
b111111 ,
b111111 1
b11 /
b111111 !
b111111 0
b111110 %
b111110 .
b111111 (
b111111 *
1'
#1600000
0'
#1610000
b100 /
b1000000 !
b1000000 0
b111111 %
b111111 .
b1000000 $
b1000000 ,
b1000000 1
b1000000 (
b1000000 *
1'
#1620000
0'
#1630000
b1000001 $
b1000001 ,
b1000001 1
b0 /
0#
b1000001 !
b1000001 0
b1000000 %
b1000000 .
b1000001 (
b1000001 *
1'
#1640000
0'
#1650000
1#
1'
#1660000
0'
#1670000
b1000010 $
b1000010 ,
b1000010 1
b1 /
b1000010 !
b1000010 0
b1000001 %
b1000001 .
b1000010 (
b1000010 *
1'
#1680000
0'
#1690000
b10 /
b1000011 !
b1000011 0
b1000010 %
b1000010 .
b1000011 $
b1000011 ,
b1000011 1
b1000011 (
b1000011 *
1'
#1700000
0'
#1710000
b1000100 $
b1000100 ,
b1000100 1
b11 /
b1000100 !
b1000100 0
b1000011 %
b1000011 .
b1000100 (
b1000100 *
1'
#1720000
0'
#1730000
b100 /
b1000101 !
b1000101 0
b1000100 %
b1000100 .
b1000101 $
b1000101 ,
b1000101 1
b1000101 (
b1000101 *
1'
#1740000
0'
#1750000
b1000110 $
b1000110 ,
b1000110 1
b0 /
0#
b1000110 !
b1000110 0
b1000101 %
b1000101 .
b1000110 (
b1000110 *
1'
#1760000
0'
#1770000
1#
1'
#1780000
0'
#1790000
b1000111 $
b1000111 ,
b1000111 1
b1 /
b1000111 !
b1000111 0
b1000110 %
b1000110 .
b1000111 (
b1000111 *
1'
#1800000
0'
#1810000
b10 /
b1001000 !
b1001000 0
b1000111 %
b1000111 .
b1001000 $
b1001000 ,
b1001000 1
b1001000 (
b1001000 *
1'
#1820000
0'
#1830000
b1001001 $
b1001001 ,
b1001001 1
b11 /
b1001001 !
b1001001 0
b1001000 %
b1001000 .
b1001001 (
b1001001 *
1'
#1840000
0'
#1850000
b100 /
b1001010 !
b1001010 0
b1001001 %
b1001001 .
b1001010 $
b1001010 ,
b1001010 1
b1001010 (
b1001010 *
1'
#1860000
0'
#1870000
b1001011 $
b1001011 ,
b1001011 1
b0 /
0#
b1001011 !
b1001011 0
b1001010 %
b1001010 .
b1001011 (
b1001011 *
1'
#1880000
0'
#1890000
1#
1'
#1900000
0'
#1910000
b1001100 $
b1001100 ,
b1001100 1
b1 /
b1001100 !
b1001100 0
b1001011 %
b1001011 .
b1001100 (
b1001100 *
1'
#1920000
0'
#1930000
b10 /
b1001101 !
b1001101 0
b1001100 %
b1001100 .
b1001101 $
b1001101 ,
b1001101 1
b1001101 (
b1001101 *
1'
#1940000
0'
#1950000
b1001110 $
b1001110 ,
b1001110 1
b11 /
b1001110 !
b1001110 0
b1001101 %
b1001101 .
b1001110 (
b1001110 *
1'
#1960000
0'
#1970000
b100 /
b1001111 !
b1001111 0
b1001110 %
b1001110 .
b1001111 $
b1001111 ,
b1001111 1
b1001111 (
b1001111 *
1'
#1980000
0'
#1990000
b1010000 $
b1010000 ,
b1010000 1
b0 /
0#
b1010000 !
b1010000 0
b1001111 %
b1001111 .
b1010000 (
b1010000 *
1'
#2000000
0'
#2010000
1#
1'
#2020000
0'
#2030000
b1010001 $
b1010001 ,
b1010001 1
b1 /
b1010001 !
b1010001 0
b1010000 %
b1010000 .
b1010001 (
b1010001 *
1'
#2040000
0'
#2050000
b10 /
b1010010 !
b1010010 0
b1010001 %
b1010001 .
b1010010 $
b1010010 ,
b1010010 1
b1010010 (
b1010010 *
1'
#2060000
0'
#2070000
b1010011 $
b1010011 ,
b1010011 1
b11 /
b1010011 !
b1010011 0
b1010010 %
b1010010 .
b1010011 (
b1010011 *
1'
#2080000
0'
#2090000
b100 /
b1010100 !
b1010100 0
b1010011 %
b1010011 .
b1010100 $
b1010100 ,
b1010100 1
b1010100 (
b1010100 *
1'
#2100000
0'
#2110000
b1010101 $
b1010101 ,
b1010101 1
b0 /
0#
b1010101 !
b1010101 0
b1010100 %
b1010100 .
b1010101 (
b1010101 *
1'
#2120000
0'
#2130000
1#
1'
#2140000
0'
#2150000
b1010110 $
b1010110 ,
b1010110 1
b1 /
b1010110 !
b1010110 0
b1010101 %
b1010101 .
b1010110 (
b1010110 *
1'
#2160000
0'
#2170000
b10 /
b1010111 !
b1010111 0
b1010110 %
b1010110 .
b1010111 $
b1010111 ,
b1010111 1
b1010111 (
b1010111 *
1'
#2180000
0'
#2190000
b1011000 $
b1011000 ,
b1011000 1
b11 /
b1011000 !
b1011000 0
b1010111 %
b1010111 .
b1011000 (
b1011000 *
1'
#2200000
0'
#2210000
b100 /
b1011001 !
b1011001 0
b1011000 %
b1011000 .
b1011001 $
b1011001 ,
b1011001 1
b1011001 (
b1011001 *
1'
#2220000
0'
#2230000
b1011010 $
b1011010 ,
b1011010 1
b0 /
0#
b1011010 !
b1011010 0
b1011001 %
b1011001 .
b1011010 (
b1011010 *
1'
#2240000
0'
#2250000
1#
1'
#2260000
0'
#2270000
b1011011 $
b1011011 ,
b1011011 1
b1 /
b1011011 !
b1011011 0
b1011010 %
b1011010 .
b1011011 (
b1011011 *
1'
#2280000
0'
#2290000
b10 /
b1011100 !
b1011100 0
b1011011 %
b1011011 .
b1011100 $
b1011100 ,
b1011100 1
b1011100 (
b1011100 *
1'
#2300000
0'
#2310000
b1011101 $
b1011101 ,
b1011101 1
b11 /
b1011101 !
b1011101 0
b1011100 %
b1011100 .
b1011101 (
b1011101 *
1'
#2320000
0'
#2330000
b100 /
b1011110 !
b1011110 0
b1011101 %
b1011101 .
b1011110 $
b1011110 ,
b1011110 1
b1011110 (
b1011110 *
1'
#2340000
0'
#2350000
b1011111 $
b1011111 ,
b1011111 1
b0 /
0#
b1011111 !
b1011111 0
b1011110 %
b1011110 .
b1011111 (
b1011111 *
1'
#2360000
0'
#2370000
1#
1'
#2380000
0'
#2390000
b1100000 $
b1100000 ,
b1100000 1
b1 /
b1100000 !
b1100000 0
b1011111 %
b1011111 .
b1100000 (
b1100000 *
1'
#2400000
0'
#2410000
b10 /
b1100001 !
b1100001 0
b1100000 %
b1100000 .
b1100001 $
b1100001 ,
b1100001 1
b1100001 (
b1100001 *
1'
#2420000
0'
#2430000
b1100010 $
b1100010 ,
b1100010 1
b11 /
b1100010 !
b1100010 0
b1100001 %
b1100001 .
b1100010 (
b1100010 *
1'
#2440000
0'
#2450000
b100 /
b1100011 !
b1100011 0
b1100010 %
b1100010 .
b1100011 $
b1100011 ,
b1100011 1
b1100011 (
b1100011 *
1'
#2460000
0'
#2470000
b1100100 $
b1100100 ,
b1100100 1
b0 /
0#
b1100100 !
b1100100 0
b1100011 %
b1100011 .
b1100100 (
b1100100 *
1'
#2480000
0'
#2490000
1#
1'
#2500000
0'
#2510000
b1100101 $
b1100101 ,
b1100101 1
b1 /
b1100101 !
b1100101 0
b1100100 %
b1100100 .
b1100101 (
b1100101 *
1'
#2520000
0'
#2530000
b10 /
b1100110 !
b1100110 0
b1100101 %
b1100101 .
b1100110 $
b1100110 ,
b1100110 1
b1100110 (
b1100110 *
1'
#2540000
0'
#2550000
b1100111 $
b1100111 ,
b1100111 1
b11 /
b1100111 !
b1100111 0
b1100110 %
b1100110 .
b1100111 (
b1100111 *
1'
#2560000
0'
#2570000
b100 /
b1101000 !
b1101000 0
b1100111 %
b1100111 .
b1101000 $
b1101000 ,
b1101000 1
b1101000 (
b1101000 *
1'
#2580000
0'
#2590000
b1101001 $
b1101001 ,
b1101001 1
b0 /
0#
b1101001 !
b1101001 0
b1101000 %
b1101000 .
b1101001 (
b1101001 *
1'
#2600000
0'
#2610000
1#
1'
#2620000
0'
#2630000
b1101010 $
b1101010 ,
b1101010 1
b1 /
b1101010 !
b1101010 0
b1101001 %
b1101001 .
b1101010 (
b1101010 *
1'
#2640000
0'
#2650000
b10 /
b1101011 !
b1101011 0
b1101010 %
b1101010 .
b1101011 $
b1101011 ,
b1101011 1
b1101011 (
b1101011 *
1'
#2660000
0'
#2670000
b1101100 $
b1101100 ,
b1101100 1
b11 /
b1101100 !
b1101100 0
b1101011 %
b1101011 .
b1101100 (
b1101100 *
1'
#2680000
0'
#2690000
b100 /
b1101101 !
b1101101 0
b1101100 %
b1101100 .
b1101101 $
b1101101 ,
b1101101 1
b1101101 (
b1101101 *
1'
#2700000
0'
#2710000
b1101110 $
b1101110 ,
b1101110 1
b0 /
0#
b1101110 !
b1101110 0
b1101101 %
b1101101 .
b1101110 (
b1101110 *
1'
#2720000
0'
#2730000
1#
1'
#2740000
0'
#2750000
b1101111 $
b1101111 ,
b1101111 1
b1 /
b1101111 !
b1101111 0
b1101110 %
b1101110 .
b1101111 (
b1101111 *
1'
#2760000
0'
#2770000
b10 /
b1110000 !
b1110000 0
b1101111 %
b1101111 .
b1110000 $
b1110000 ,
b1110000 1
b1110000 (
b1110000 *
1'
#2780000
0'
#2790000
b1110001 $
b1110001 ,
b1110001 1
b11 /
b1110001 !
b1110001 0
b1110000 %
b1110000 .
b1110001 (
b1110001 *
1'
#2800000
0'
#2810000
b100 /
b1110010 !
b1110010 0
b1110001 %
b1110001 .
b1110010 $
b1110010 ,
b1110010 1
b1110010 (
b1110010 *
1'
#2820000
0'
#2830000
b1110011 $
b1110011 ,
b1110011 1
b0 /
0#
b1110011 !
b1110011 0
b1110010 %
b1110010 .
b1110011 (
b1110011 *
1'
#2840000
0'
#2850000
1#
1'
#2860000
0'
#2870000
b1110100 $
b1110100 ,
b1110100 1
b1 /
b1110100 !
b1110100 0
b1110011 %
b1110011 .
b1110100 (
b1110100 *
1'
#2880000
0'
#2890000
b10 /
b1110101 !
b1110101 0
b1110100 %
b1110100 .
b1110101 $
b1110101 ,
b1110101 1
b1110101 (
b1110101 *
1'
#2900000
0'
#2910000
b1110110 $
b1110110 ,
b1110110 1
b11 /
b1110110 !
b1110110 0
b1110101 %
b1110101 .
b1110110 (
b1110110 *
1'
#2920000
0'
#2930000
b100 /
b1110111 !
b1110111 0
b1110110 %
b1110110 .
b1110111 $
b1110111 ,
b1110111 1
b1110111 (
b1110111 *
1'
#2940000
0'
#2950000
b1111000 $
b1111000 ,
b1111000 1
b0 /
0#
b1111000 !
b1111000 0
b1110111 %
b1110111 .
b1111000 (
b1111000 *
1'
#2960000
0'
#2970000
1#
1'
#2980000
0'
#2990000
b1111001 $
b1111001 ,
b1111001 1
b1 /
b1111001 !
b1111001 0
b1111000 %
b1111000 .
b1111001 (
b1111001 *
1'
#3000000
0'
#3010000
b10 /
b1111010 !
b1111010 0
b1111001 %
b1111001 .
b1111010 $
b1111010 ,
b1111010 1
b1111010 (
b1111010 *
1'
#3020000
0'
#3030000
b1111011 $
b1111011 ,
b1111011 1
b11 /
b1111011 !
b1111011 0
b1111010 %
b1111010 .
b1111011 (
b1111011 *
1'
#3040000
0'
#3050000
b100 /
b1111100 !
b1111100 0
b1111011 %
b1111011 .
b1111100 $
b1111100 ,
b1111100 1
b1111100 (
b1111100 *
1'
#3060000
0'
#3070000
b1111101 $
b1111101 ,
b1111101 1
b0 /
0#
b1111101 !
b1111101 0
b1111100 %
b1111100 .
b1111101 (
b1111101 *
1'
#3080000
0'
#3090000
1#
1'
#3100000
0'
#3110000
b1111110 $
b1111110 ,
b1111110 1
b1 /
b1111110 !
b1111110 0
b1111101 %
b1111101 .
b1111110 (
b1111110 *
1'
#3120000
0'
#3130000
b10 /
b1111111 !
b1111111 0
b1111110 %
b1111110 .
b1111111 $
b1111111 ,
b1111111 1
b1111111 (
b1111111 *
1'
#3140000
0'
#3150000
b10000000 $
b10000000 ,
b10000000 1
b11 /
b10000000 !
b10000000 0
b1111111 %
b1111111 .
b10000000 (
b10000000 *
1'
#3160000
0'
#3170000
b100 /
b10000001 !
b10000001 0
b10000000 %
b10000000 .
b10000001 $
b10000001 ,
b10000001 1
b10000001 (
b10000001 *
1'
#3180000
0'
#3190000
b10000010 $
b10000010 ,
b10000010 1
b0 /
0#
b10000010 !
b10000010 0
b10000001 %
b10000001 .
b10000010 (
b10000010 *
1'
#3200000
0'
#3210000
1#
1'
#3220000
0'
#3230000
b10000011 $
b10000011 ,
b10000011 1
b1 /
b10000011 !
b10000011 0
b10000010 %
b10000010 .
b10000011 (
b10000011 *
1'
#3240000
0'
#3250000
b10 /
b10000100 !
b10000100 0
b10000011 %
b10000011 .
b10000100 $
b10000100 ,
b10000100 1
b10000100 (
b10000100 *
1'
#3260000
0'
#3270000
b10000101 $
b10000101 ,
b10000101 1
b11 /
b10000101 !
b10000101 0
b10000100 %
b10000100 .
b10000101 (
b10000101 *
1'
#3280000
0'
#3290000
b100 /
b10000110 !
b10000110 0
b10000101 %
b10000101 .
b10000110 $
b10000110 ,
b10000110 1
b10000110 (
b10000110 *
1'
#3300000
0'
#3310000
b10000111 $
b10000111 ,
b10000111 1
b0 /
0#
b10000111 !
b10000111 0
b10000110 %
b10000110 .
b10000111 (
b10000111 *
1'
#3320000
0'
#3330000
1#
1'
#3340000
0'
#3350000
b10001000 $
b10001000 ,
b10001000 1
b1 /
b10001000 !
b10001000 0
b10000111 %
b10000111 .
b10001000 (
b10001000 *
1'
#3360000
0'
#3370000
b10 /
b10001001 !
b10001001 0
b10001000 %
b10001000 .
b10001001 $
b10001001 ,
b10001001 1
b10001001 (
b10001001 *
1'
#3380000
0'
#3390000
b10001010 $
b10001010 ,
b10001010 1
b11 /
b10001010 !
b10001010 0
b10001001 %
b10001001 .
b10001010 (
b10001010 *
1'
#3400000
0'
#3410000
b100 /
b10001011 !
b10001011 0
b10001010 %
b10001010 .
b10001011 $
b10001011 ,
b10001011 1
b10001011 (
b10001011 *
1'
#3420000
0'
#3430000
b10001100 $
b10001100 ,
b10001100 1
b0 /
0#
b10001100 !
b10001100 0
b10001011 %
b10001011 .
b10001100 (
b10001100 *
1'
#3440000
0'
#3450000
1#
1'
#3460000
0'
